typhoon/__init__.py
typhoon/main.py
typhoon/utils/__init__.py
typhoon/utils/bcolors.py
typhoon/utils/calculations.py
typhoon/utils/communication.py
typhoon/utils/config.py
typhoon_robotic_arm-1.0.3.dist-info/LICENCE
typhoon_robotic_arm-1.0.3.dist-info/METADATA
typhoon_robotic_arm-1.0.3.dist-info/WHEEL
typhoon_robotic_arm-1.0.3.dist-info/top_level.txt
typhoon_robotic_arm-1.0.3.dist-info/RECORD
