Metadata-Version: 2.1
Name: typhoon-robotic-arm
Version: 1.0.3
Summary: Library to communicate with Typhoon robotic arm.
Author-email: Tomas Sedlak <t.sedlak.24@gmail.com>
Project-URL: Homepage, https://github.com/tomas-sedlak/typhoon
Project-URL: Issues, https://github.com/tomas-sedlak/typhoon/issues
Classifier: Programming Language :: Python :: 3
Classifier: License :: OSI Approved :: MIT License
Classifier: Operating System :: OS Independent
Requires-Python: >=3.8
License-File: LICENCE
Requires-Dist: pyserial
